{
	"configurations" : 
	[
		{
			"directories" : 
			[
				{
					"build" : ".",
					"childIndexes" : 
					[
						1,
						2,
						3,
						5,
						6,
						7,
						10
					],
					"hasInstallRule" : true,
					"jsonFile" : "directory-.-Debug-d0094a50bb2071803777.json",
					"minimumCMakeVersion" : 
					{
						"string" : "3.10"
					},
					"projectIndex" : 0,
					"source" : ".",
					"targetIndexes" : 
					[
						10,
						11
					]
				},
				{
					"build" : "_deps/gamepad-build",
					"hasInstallRule" : true,
					"jsonFile" : "directory-_deps.gamepad-build-Debug-ee1704f784067bebaf70.json",
					"minimumCMakeVersion" : 
					{
						"string" : "3.5"
					},
					"parentIndex" : 0,
					"projectIndex" : 1,
					"source" : "cmake-build-debug/_deps/gamepad-src",
					"targetIndexes" : 
					[
						1,
						2,
						8
					]
				},
				{
					"build" : "data",
					"jsonFile" : "directory-data-Debug-9297ce871a875605ab09.json",
					"minimumCMakeVersion" : 
					{
						"string" : "3.10"
					},
					"parentIndex" : 0,
					"projectIndex" : 2,
					"source" : "data",
					"targetIndexes" : 
					[
						0
					]
				},
				{
					"build" : "io",
					"childIndexes" : 
					[
						4
					],
					"jsonFile" : "directory-io-Debug-f70c811dfb55af01b35e.json",
					"minimumCMakeVersion" : 
					{
						"string" : "3.10"
					},
					"parentIndex" : 0,
					"projectIndex" : 3,
					"source" : "io"
				},
				{
					"build" : "io/interface",
					"jsonFile" : "directory-io.interface-Debug-aa6f6f9e3241bc544edf.json",
					"minimumCMakeVersion" : 
					{
						"string" : "3.10"
					},
					"parentIndex" : 3,
					"projectIndex" : 3,
					"source" : "io/interface",
					"targetIndexes" : 
					[
						7
					]
				},
				{
					"build" : "logic",
					"jsonFile" : "directory-logic-Debug-b3c5c1d83ea795280125.json",
					"minimumCMakeVersion" : 
					{
						"string" : "3.10"
					},
					"parentIndex" : 0,
					"projectIndex" : 4,
					"source" : "logic",
					"targetIndexes" : 
					[
						9
					]
				},
				{
					"build" : "tests",
					"jsonFile" : "directory-tests-Debug-70e4927a02b591d5c1f8.json",
					"minimumCMakeVersion" : 
					{
						"string" : "3.10"
					},
					"parentIndex" : 0,
					"projectIndex" : 5,
					"source" : "tests",
					"targetIndexes" : 
					[
						12
					]
				},
				{
					"build" : "_deps/googletest-build",
					"childIndexes" : 
					[
						8
					],
					"hasInstallRule" : true,
					"jsonFile" : "directory-_deps.googletest-build-Debug-ded26adebee9516e95c3.json",
					"minimumCMakeVersion" : 
					{
						"string" : "3.16"
					},
					"parentIndex" : 0,
					"projectIndex" : 6,
					"source" : "cmake-build-debug/_deps/googletest-src"
				},
				{
					"build" : "_deps/googletest-build/googlemock",
					"childIndexes" : 
					[
						9
					],
					"hasInstallRule" : true,
					"jsonFile" : "directory-_deps.googletest-build.googlemock-Debug-42f2c858bcbde1baa67c.json",
					"minimumCMakeVersion" : 
					{
						"string" : "3.13"
					},
					"parentIndex" : 7,
					"projectIndex" : 7,
					"source" : "cmake-build-debug/_deps/googletest-src/googlemock",
					"targetIndexes" : 
					[
						3,
						4
					]
				},
				{
					"build" : "_deps/googletest-build/googletest",
					"hasInstallRule" : true,
					"jsonFile" : "directory-_deps.googletest-build.googletest-Debug-88a985eb21a844885ea9.json",
					"minimumCMakeVersion" : 
					{
						"string" : "3.13"
					},
					"parentIndex" : 8,
					"projectIndex" : 8,
					"source" : "cmake-build-debug/_deps/googletest-src/googletest",
					"targetIndexes" : 
					[
						5,
						6
					]
				},
				{
					"build" : "_deps/json-build",
					"jsonFile" : "directory-_deps.json-build-Debug-d5e35791dc1564e3ec77.json",
					"minimumCMakeVersion" : 
					{
						"string" : "3.5"
					},
					"parentIndex" : 0,
					"projectIndex" : 9,
					"source" : "cmake-build-debug/_deps/json-src"
				}
			],
			"name" : "Debug",
			"projects" : 
			[
				{
					"childIndexes" : 
					[
						1,
						2,
						3,
						4,
						5,
						6,
						9
					],
					"directoryIndexes" : 
					[
						0
					],
					"name" : "punto-steering-control",
					"targetIndexes" : 
					[
						10,
						11
					]
				},
				{
					"directoryIndexes" : 
					[
						1
					],
					"name" : "libgamepad",
					"parentIndex" : 0,
					"targetIndexes" : 
					[
						1,
						2,
						8
					]
				},
				{
					"directoryIndexes" : 
					[
						2
					],
					"name" : "data",
					"parentIndex" : 0,
					"targetIndexes" : 
					[
						0
					]
				},
				{
					"directoryIndexes" : 
					[
						3,
						4
					],
					"name" : "io",
					"parentIndex" : 0,
					"targetIndexes" : 
					[
						7
					]
				},
				{
					"directoryIndexes" : 
					[
						5
					],
					"name" : "logic",
					"parentIndex" : 0,
					"targetIndexes" : 
					[
						9
					]
				},
				{
					"directoryIndexes" : 
					[
						6
					],
					"name" : "tests",
					"parentIndex" : 0,
					"targetIndexes" : 
					[
						12
					]
				},
				{
					"childIndexes" : 
					[
						7
					],
					"directoryIndexes" : 
					[
						7
					],
					"name" : "googletest-distribution",
					"parentIndex" : 0
				},
				{
					"childIndexes" : 
					[
						8
					],
					"directoryIndexes" : 
					[
						8
					],
					"name" : "gmock",
					"parentIndex" : 6,
					"targetIndexes" : 
					[
						3,
						4
					]
				},
				{
					"directoryIndexes" : 
					[
						9
					],
					"name" : "gtest",
					"parentIndex" : 7,
					"targetIndexes" : 
					[
						5,
						6
					]
				},
				{
					"directoryIndexes" : 
					[
						10
					],
					"name" : "nlohmann_json",
					"parentIndex" : 0
				}
			],
			"targets" : 
			[
				{
					"directoryIndex" : 2,
					"id" : "data::@efda893aa850b0c0e61f",
					"jsonFile" : "target-data-Debug-991c319047242e74c90e.json",
					"name" : "data",
					"projectIndex" : 2
				},
				{
					"directoryIndex" : 1,
					"id" : "gamepad::@2e0a17c524402fff685a",
					"jsonFile" : "target-gamepad-Debug-faf38602946f3358ea1a.json",
					"name" : "gamepad",
					"projectIndex" : 1
				},
				{
					"directoryIndex" : 1,
					"id" : "gamepad_static::@2e0a17c524402fff685a",
					"jsonFile" : "target-gamepad_static-Debug-8a3b6ce6fbf88b9504f5.json",
					"name" : "gamepad_static",
					"projectIndex" : 1
				},
				{
					"directoryIndex" : 8,
					"id" : "gmock::@0f7bb11d64f3678238c7",
					"jsonFile" : "target-gmock-Debug-130cc4308966e00ba07c.json",
					"name" : "gmock",
					"projectIndex" : 7
				},
				{
					"directoryIndex" : 8,
					"id" : "gmock_main::@0f7bb11d64f3678238c7",
					"jsonFile" : "target-gmock_main-Debug-ea9298b3358ca9c02cd8.json",
					"name" : "gmock_main",
					"projectIndex" : 7
				},
				{
					"directoryIndex" : 9,
					"id" : "gtest::@1ea2dfc0605fe3ab2a3f",
					"jsonFile" : "target-gtest-Debug-b41402624cef429faf8c.json",
					"name" : "gtest",
					"projectIndex" : 8
				},
				{
					"directoryIndex" : 9,
					"id" : "gtest_main::@1ea2dfc0605fe3ab2a3f",
					"jsonFile" : "target-gtest_main-Debug-74b1d7cf67ccd2d0546f.json",
					"name" : "gtest_main",
					"projectIndex" : 8
				},
				{
					"directoryIndex" : 4,
					"id" : "interface_lib::@75e3086d0247a44e4d23",
					"jsonFile" : "target-interface_lib-Debug-7a023d1d3bd0948c353c.json",
					"name" : "interface_lib",
					"projectIndex" : 3
				},
				{
					"directoryIndex" : 1,
					"id" : "libgamepad_tests::@2e0a17c524402fff685a",
					"jsonFile" : "target-libgamepad_tests-Debug-50516a06f2a44473d104.json",
					"name" : "libgamepad_tests",
					"projectIndex" : 1
				},
				{
					"directoryIndex" : 5,
					"id" : "logic_lib::@330d13901b3cda70f4f4",
					"jsonFile" : "target-logic_lib-Debug-bdc3556a5885c492a2e6.json",
					"name" : "logic_lib",
					"projectIndex" : 4
				},
				{
					"directoryIndex" : 0,
					"id" : "main::@6890427a1f51a3e7e1df",
					"jsonFile" : "target-main-Debug-7b821464fe72390699d7.json",
					"name" : "main",
					"projectIndex" : 0
				},
				{
					"directoryIndex" : 0,
					"id" : "standard_tests::@6890427a1f51a3e7e1df",
					"jsonFile" : "target-standard_tests-Debug-41bfef167ce49b1d1817.json",
					"name" : "standard_tests",
					"projectIndex" : 0
				},
				{
					"directoryIndex" : 6,
					"id" : "tests::@a44f0ac069e85531cdee",
					"jsonFile" : "target-tests-Debug-99184bcee3e010a5f278.json",
					"name" : "tests",
					"projectIndex" : 5
				}
			]
		}
	],
	"kind" : "codemodel",
	"paths" : 
	{
		"build" : "C:/Users/oliwi/wallslayers/punto-steering-control/cmake-build-debug",
		"source" : "C:/Users/oliwi/wallslayers/punto-steering-control"
	},
	"version" : 
	{
		"major" : 2,
		"minor" : 7
	}
}
